StellarDS.py
stellards-0.0.1.1.dist-info/METADATA
stellards-0.0.1.1.dist-info/WHEEL
stellards-0.0.1.1.dist-info/licenses/LICENSE
stellards-0.0.1.1.dist-info/RECORD
