Metadata-Version: 2.3
Name: StellarDS
Version: 0.0.1.1
Summary: StellarDS.io SDK for Python
Project-URL: Homepage, https://github.com/TMS-Software-Python/StellarDS-SDK
Project-URL: Issues, https://github.com/TMS-Software-Python/StellarDS-SDK/issues
Author-email: StellarDS <info@stellards.io>
License-File: LICENSE
Classifier: License :: OSI Approved :: MIT License
Classifier: Operating System :: OS Independent
Classifier: Programming Language :: Python :: 3
Requires-Python: >=3.8
